keepdb_tuhoa/__init__.py
keepdb_tuhoa/management/__init__.py
keepdb_tuhoa/management/commands/__init__.py
keepdb_tuhoa/management/commands/test.py
django_keepdb_tuhoa-0.1.dist-info/METADATA
django_keepdb_tuhoa-0.1.dist-info/WHEEL
django_keepdb_tuhoa-0.1.dist-info/entry_points.txt
django_keepdb_tuhoa-0.1.dist-info/historia.json
django_keepdb_tuhoa-0.1.dist-info/top_level.txt
django_keepdb_tuhoa-0.1.dist-info/RECORD
