Metadata-Version: 2.1
Name: django-keepdb-tuhoa
Version: 0.1
Summary: Djangon test-ylläpitokomennon laajennos
Home-page: https://github.com/an7oine/django-keepdb-tuhoa.git
Author: Antti Hautaniemi
Author-email: antti.hautaniemi@me.com
License: MIT
Requires-Python: >=3.8
Requires-Dist: django >=4.2
